README.md
setup.py
cg_odme/__init__.py
cg_odme/calibration.py
cg_odme/data.py
cg_odme/run.py
cg_odme.egg-info/PKG-INFO
cg_odme.egg-info/SOURCES.txt
cg_odme.egg-info/dependency_links.txt
cg_odme.egg-info/not-zip-safe
cg_odme.egg-info/top_level.txt