Metadata-Version: 2.1
Name: cg-odme
Version: 0.1
Summary: Calibrate optimal path flows using systematic mapping variables
Author: Taehooie Kim and Dr. Xuesong (Simon) Zhou
